cv2/HeteroPlugin.dll
cv2/HeteroPlugin.exp
cv2/HeteroPlugin.lib
cv2/LICENSE-3RD-PARTY.txt
cv2/LICENSE.txt
cv2/XLink.lib
cv2/__init__.py
cv2/cpu_extension.dll
cv2/cpu_extension.exp
cv2/cpu_extension.lib
cv2/cv2.cp35-win_amd64.pyd
cv2/fluid.lib
cv2/format_reader.dll
cv2/format_reader.exp
cv2/format_reader.lib
cv2/gflags_nothreads_static.lib
cv2/inference_engine.dll
cv2/inference_engine.exp
cv2/inference_engine.lib
cv2/inference_engine_s.lib
cv2/mock_engine.dll
cv2/mock_engine.exp
cv2/mock_engine.lib
cv2/opencv_videoio_ffmpeg411_64.dll
cv2/openvino.patch
cv2/pugixml.lib
cv2/pugixml_mt.lib
cv2/stb_image.lib
cv2/data/__init__.py
cv2/data/haarcascade_eye.xml
cv2/data/haarcascade_eye_tree_eyeglasses.xml
cv2/data/haarcascade_frontalcatface.xml
cv2/data/haarcascade_frontalcatface_extended.xml
cv2/data/haarcascade_frontalface_alt.xml
cv2/data/haarcascade_frontalface_alt2.xml
cv2/data/haarcascade_frontalface_alt_tree.xml
cv2/data/haarcascade_frontalface_default.xml
cv2/data/haarcascade_fullbody.xml
cv2/data/haarcascade_lefteye_2splits.xml
cv2/data/haarcascade_licence_plate_rus_16stages.xml
cv2/data/haarcascade_lowerbody.xml
cv2/data/haarcascade_profileface.xml
cv2/data/haarcascade_righteye_2splits.xml
cv2/data/haarcascade_russian_plate_number.xml
cv2/data/haarcascade_smile.xml
cv2/data/haarcascade_upperbody.xml
opencv_openvino_contrib_python-4.1.1.26.dist-info/LICENSE-3RD-PARTY.txt
opencv_openvino_contrib_python-4.1.1.26.dist-info/LICENSE.txt
opencv_openvino_contrib_python-4.1.1.26.dist-info/METADATA
opencv_openvino_contrib_python-4.1.1.26.dist-info/WHEEL
opencv_openvino_contrib_python-4.1.1.26.dist-info/top_level.txt
opencv_openvino_contrib_python-4.1.1.26.dist-info/RECORD
